[["Map",1,2,9,10,126,127],"meta::meta",["Map",3,4,5,6,7,8],"astro-version","5.17.1","content-config-digest","e4cfa0c1f19b86de","astro-config-digest","{\"root\":{},\"srcDir\":{},\"publicDir\":{},\"outDir\":{},\"cacheDir\":{},\"site\":\"https://test-hjemmeside.vercel.app\",\"compressHTML\":true,\"base\":\"/\",\"trailingSlash\":\"ignore\",\"output\":\"server\",\"scopedStyleStrategy\":\"attribute\",\"build\":{\"format\":\"directory\",\"client\":{},\"server\":{},\"assets\":\"_astro\",\"serverEntry\":\"entry.mjs\",\"redirects\":false,\"inlineStylesheets\":\"auto\",\"concurrency\":1},\"server\":{\"open\":false,\"host\":false,\"port\":4321,\"streaming\":true,\"allowedHosts\":[]},\"redirects\":{},\"image\":{\"endpoint\":{\"route\":\"/_image\"},\"service\":{\"entrypoint\":\"astro/assets/services/sharp\",\"config\":{}},\"domains\":[],\"remotePatterns\":[],\"responsiveStyles\":false},\"devToolbar\":{\"enabled\":true},\"markdown\":{\"syntaxHighlight\":{\"type\":\"shiki\",\"excludeLangs\":[\"math\"]},\"shikiConfig\":{\"langs\":[],\"langAlias\":{},\"theme\":\"github-dark\",\"themes\":{},\"wrap\":false,\"transformers\":[]},\"remarkPlugins\":[],\"rehypePlugins\":[],\"remarkRehype\":{},\"gfm\":true,\"smartypants\":true},\"security\":{\"checkOrigin\":true,\"allowedDomains\":[]},\"env\":{\"schema\":{},\"validateSecrets\":false},\"experimental\":{\"clientPrerender\":false,\"contentIntellisense\":false,\"headingIdCompat\":false,\"preserveScriptOrder\":false,\"liveContentCollections\":false,\"csp\":false,\"staticImportMetaEnv\":false,\"chromeDevtoolsWorkspace\":false,\"failOnPrerenderConflict\":false,\"svgo\":false},\"legacy\":{\"collections\":false}}","projects",["Map",11,12,27,28,42,43,57,58,70,71,82,83,94,95,104,105,115,116],"agf-fan",{"id":11,"data":13,"body":23,"filePath":24,"digest":25,"legacyId":26,"deferredRender":22},{"title":14,"shortDescription":15,"link":16,"year":17,"tags":18,"highlight":22},"Kæmpe agf fan","I 2026 vinder agf Superligaen.","#","2026",[19,20,21],"Fodbold","AGF","Superligaen",true,"AGF vinder guld.","src/content/projects/agf-fan.mdoc","94adcddcd4f0a5d2","agf-fan.mdoc","ecommerce-dashboard",{"id":27,"data":29,"body":38,"filePath":39,"digest":40,"legacyId":41,"deferredRender":22},{"title":30,"shortDescription":31,"link":16,"year":32,"tags":33,"highlight":22},"E-commerce Dashboard","Dashboard til visualisering af salgsdata bygget med React og Tremor for en lokal webshop.","2024",[34,35,36,37],"Web","React","Analyse","Frontend","Dashboard til visualisering af salgsdata.","src/content/projects/ecommerce-dashboard.mdoc","4fb9a96e5115e019","ecommerce-dashboard.mdoc","ai-automatisering",{"id":42,"data":44,"body":53,"filePath":54,"digest":55,"legacyId":56,"deferredRender":22},{"title":45,"shortDescription":46,"link":16,"year":47,"tags":48,"highlight":22},"AI Automatiserings-workflow","Et komplet n8n workflow der automatiserer kundesupport baseret på indgående emails og AI-analyse.","2025",[49,50,51,52],"Automatisering","n8n","AI","Python","Dette er et komplet n8n workflow der automatiserer kundesupport.","src/content/projects/ai-automatisering.mdoc","f682f01677f794cc","ai-automatisering.mdoc","digital-rapport",{"id":57,"data":59,"body":66,"filePath":67,"digest":68,"legacyId":69,"deferredRender":22},{"title":60,"shortDescription":61,"year":62,"tags":63,"highlight":65},"Digital Transformations-rapport","Akademisk rapport om implementering af nye digitale værktøjer i SMV'er.","2023",[36,64],"Strategi",false,"Akademisk rapport om digital transformation.","src/content/projects/digital-rapport.mdoc","0977a6e1f426872c","digital-rapport.mdoc","make-integrationer",{"id":70,"data":72,"body":78,"filePath":79,"digest":80,"legacyId":81,"deferredRender":22},{"title":73,"shortDescription":74,"year":32,"tags":75,"highlight":65},"Make.com Integrationer","Forbindelse af CRM (HubSpot) med Slack notifikationer for salgsteamet.",[49,76,77],"Make.com","Integration","Forbindelse af CRM med Slack.","src/content/projects/make-integrationer.mdoc","1d3e8f769bb62e7c","make-integrationer.mdoc","portfolio-v1",{"id":82,"data":84,"body":90,"filePath":91,"digest":92,"legacyId":93,"deferredRender":22},{"title":85,"shortDescription":86,"link":16,"year":87,"tags":88,"highlight":65},"Portfolio v1","Min første portfolio side bygget i ren HTML/CSS.","2022",[34,89],"HTML/CSS","Min første portfolio side.","src/content/projects/portfolio-v1.mdoc","6d7d196d54d24507","portfolio-v1.mdoc","test",{"id":94,"data":96,"filePath":101,"digest":102,"legacyId":103,"deferredRender":22},{"title":94,"shortDescription":97,"link":98,"year":32,"tags":99,"highlight":65},"Her skriver jeg, vhad jeg gerne vil ahve der skal stå","100",[100],"Test","src/content/projects/test.mdoc","1bc1ddbde35b48b6","test.mdoc","okonomi-tracker",{"id":104,"data":106,"body":111,"filePath":112,"digest":113,"legacyId":114,"deferredRender":22},{"title":107,"shortDescription":108,"link":16,"year":62,"tags":109,"highlight":65},"Personlig Økonomi Tracker","Python script der analyserer CSV eksport fra netbank og kategoriserer udgifter automatisk.",[52,36,110],"Data","Python script til økonomi tracking.","src/content/projects/okonomi-tracker.mdoc","b9e3ca286927c652","okonomi-tracker.mdoc","mad-elsker",{"id":115,"data":117,"filePath":123,"digest":124,"legacyId":125,"deferredRender":22},{"title":118,"shortDescription":119,"year":120,"tags":121,"highlight":22},"Mad elsker","Jeg elsker at lave mad og bruger mange timer på det","199",[122],"Mad","src/content/projects/mad-elsker.mdoc","7c62642289cd5add","mad-elsker.mdoc","homepage",["Map",126,128],{"id":126,"data":129,"filePath":135,"digest":136,"legacyId":137,"deferredRender":22},{"welcomeTag":130,"heroTitle":131,"heroSubtitle":132,"heroButtonText":133,"heroImage":134},"Portfolio 2026","Rasmus Fensten","Cand.IT-studerende. Jeg forener forretning med teknologi gennem **holistisk automatisering** og **AI-drevet strategi**. Derudover så elsker jeg at prøve nye **ting**.","Se Projekter","/heroImage.png","src/content/homepage/homepage.mdoc","58f3721985e1ec97","homepage.mdoc"]